pydbbackups/__init__.py
pydbbackups/backups/__init__.py
pydbbackups/backups/base.py
pydbbackups/backups/mongodb.py
pydbbackups/backups/mysql.py
pydbbackups/backups/postgres.py
pydbbackups/cli/__init__.py
pydbbackups/cli/config.py
pydbbackups/cli/main.py
pydbbackups/cli/models/__init__.py
pydbbackups/cli/models/backup_data.py
pydbbackups/cli/services/__init__.py
pydbbackups/cli/services/backups.py
pydbbackups/cli/utils/__init__.py
pydbbackups/errors.py
pydbbackups-0.1.1.dist-info/LICENSE
pydbbackups-0.1.1.dist-info/METADATA
pydbbackups-0.1.1.dist-info/WHEEL
pydbbackups-0.1.1.dist-info/entry_points.txt
pydbbackups-0.1.1.dist-info/RECORD
