Metadata-Version: 2.1
Name: pydbbackups
Version: 0.1.1
Summary: DB backups handler
Home-page: https://github.com/jbuendia1y/pydbbackups
License: MIT
Keywords: backups,databases,handler,library,cli
Author: jbuendia1y
Author-email: jgamer669@gmail.com
Requires-Python: >=3.10,<4.0
Classifier: License :: OSI Approved :: MIT License
Classifier: Programming Language :: Python :: 3
Classifier: Programming Language :: Python :: 3.10
Classifier: Programming Language :: Python :: 3.11
Requires-Dist: click (>=8.1.3,<9.0.0)
Requires-Dist: inquirer (>=3.1.3,<4.0.0)
Requires-Dist: rich (>=13.3.3,<14.0.0)
Project-URL: Repository, https://github.com/jbuendia1y/pydbbackups
